LAFITE/__init__.py
LAFITE/_nbdev.py
LAFITE/lafite_wrapper.py
LAFITE/output.py
LAFITE/preprocessing.py
LAFITE/read_collapsing.py
LAFITE/reference_processing.py
LAFITE/refine.py
LAFITE/tailFinder.py
LAFITE/utils.py
LAFITE-1.0.2.dist-info/LICENSE
LAFITE-1.0.2.dist-info/METADATA
LAFITE-1.0.2.dist-info/WHEEL
LAFITE-1.0.2.dist-info/entry_points.txt
LAFITE-1.0.2.dist-info/top_level.txt
LAFITE-1.0.2.dist-info/RECORD
