Metadata-Version: 2.1
Name: LAFITE
Version: 1.0.2
Summary: Nanopore Direct RNA-seq Transcriptome Assembly
Home-page: https://github.com/TF-Chan-Lab/LAFITE/tree/main/
Author: Jizhou ZHANG
Author-email: zjzace@ourlook.com
License: Apache Software License 2.0
Keywords: Nanopore DRS transcriptome
Classifier: Development Status :: 3 - Alpha
Classifier: Intended Audience :: Developers
Classifier: Natural Language :: English
Classifier: Programming Language :: Python :: 3.11
Classifier: License :: OSI Approved :: Apache Software License
Requires-Python: >=3.11
License-File: LICENSE
Requires-Dist: pip
Requires-Dist: packaging
Requires-Dist: biopython (>=1.80)
Requires-Dist: interlap (>=0.2.7)
Requires-Dist: joblib (>=1.2.0)
Requires-Dist: numpy (>=1.23.5)
Requires-Dist: pandas (>=1.5.2)
Requires-Dist: pysam (>=0.20.0)
Requires-Dist: scikit-learn (>=1.2.0)
Requires-Dist: tqdm (==4.64.1)
Provides-Extra: dev
